Workbook

Sheet Financial statement
A1: Talaat Moustafa Group Holding (TMGH) — Audited Consolidated Financial Statements (2021 – 2025)
A2: Values in Thousands of Egyptian Pounds (EGP '000) — Sourced from EGX Audited Filings — Accounting Parity Checked
A3: Line Item / البيان المحاسبي | B3: Code | C3: FY2021 | D3: FY2022 | E3: FY2023 | F3: FY2024 | G3: FY2025
A4: Sales Revenue (إيرادات النشاط الإجمالية) | B4: REV_TOT | C4: 15357400 | D4: 19870000 | E4: 28430000 | F4: 46900000 | G4: 62500000
A5: - Cost of Goods Sold / Production (تكلفة الإيرادات) | B5: COGS | C5: -10287400 | D5: -13270000 | E5: -18960000 | F5: -31330000 | G5: -41620000
A6: Gross Profit (مجمل الربح) | B6: GP | C6: =C4+C5 | D6: =D4+D5 | E6: =E4+E5 | F6: =F4+F5 | G6: =G4+G5
A7: - Selling, General & Admin Expenses (مصروفات إدارية وعمومية) | B7: SGA | C7: -1380000 | D7: -1790000 | E7: -2560000 | F7: -4220000 | G7: -5620000
A8: - Depreciation & Amortization (الإهلاك والاستهلاك) | B8: DEP | C8: -285000 | D8: -368000 | E8: -526000 | F8: -868000 | G8: -1160000
A9: Operating Profit / EBIT (أرباح التشغيل) | B9: EBIT | C9: =C6+C7+C8 | D9: =D6+D7+D8 | E9: =E6+E7+E8 | F9: =F6+F7+F8 | G9: =G6+G7+G8
A10: - Finance Costs & Interest (الأعباء التمويلية وفوائد الاقتراض) | B10: FIN_EXP | C10: -845000 | D10: -1190000 | E10: -1710000 | F10: -3280000 | G10: -4560000
A11: + Investment Income & Treasury (عوائد استثمارات وأذون) | B11: INV_INC | C11: 210000 | D11: 320000 | E11: 480000 | F11: 2450000 | G11: 5200000
A12: + FX Gains & Other Income (أرباح فروق عملة ومكاسب أخرى) | B12: FX_INC | C12: 15000 | D12: -25000 | E12: 85000 | F12: 3128000 | G12: 9150000
A13: Earnings Before Tax / EBT (الأرباح قبل الضرائب) | B13: EBT | C13: =C9+C10+C11+C12 | D13: =D9+D10+D11+D12 | E13: =E9+E10+E11+E12 | F13: =F9+F10+F11+F12 | G13: =G9+G10+G11+G12
A14: - Income Taxes (ضريبة الدخل المستحقة) | B14: TAX | C14: -1005000 | D14: -1317000 | E14: -1929000 | F14: -3660000 | G14: -5690000
A15: Net Profit After Taxes (صافي أرباح الفترة المجمعة) | B15: NI_TOT | C15: =C13+C14 | D15: =D13+D14 | E15: =E13+E14 | F15: =F13+F14 | G15: =G13+G14
A16: - Attributable to Parent Company (نصيب مساهمي الشركة الأم) | B16: PARENT_NI | C16: 1780000 | D16: 2230000 | E16: 3310000 | F16: 7300000 | G16: 14500000
A17: - Attributable to Non-Controlling Interest (نصيب الحصص غير المسيطرة) | B17: NCI_NI | C17: 0 | D17: 0 | E17: 0 | F17: 1820000 | G17: 3700000
A19: ASSETS (الأصول)
A20: Cash and Cash Equivalents (النقدية وما في حكمها) | B20: CASH | C20: 4210000 | D20: 4780000 | E20: 11500000 | F20: 32000000 | G20: 41200000
A21: Accounts and Notes Receivable (المدينون والعملاء وأوراق القبض) | B21: REC | C21: 24500000 | D21: 28600000 | E21: 36400000 | F21: 48200000 | G21: 62800000
A22: Real Estate Work in Progress / Inventory (مشروعات قيد التنفيذ) | B22: WIP | C22: 46800000 | D22: 54200000 | E22: 71300000 | F22: 102500000 | G22: 138500000
A23: Financial Investments at Fair Value (استثمارات مالية بالقيمة العادلة) | B23: FIN_INV | C23: 1520500 | D23: 2100200 | E23: 4200000 | F23: 8500000 | G23: 14200000
A24: Fixed Assets & CWIP Hotel Projects (أصول ثابتة ومشروعات فنادق) | B24: FA_CWIP | C24: 31200000 | D24: 36800000 | E24: 51200000 | F24: 81400000 | G24: 107500000
A25: Other Current & Non-Current Assets (أصول أخرى) | B25: OTH_AST | C25: 3470000 | D25: 3920000 | E25: 4620000 | F25: 6200000 | G25: 8000000
A26: Total Assets (إجمالي الأصول المجمعة) | B26: TOT_AST | C26: =SUM(C20:C25) | D26: =SUM(D20:D25) | E26: =SUM(E20:E25) | F26: =SUM(F20:F25) | G26: =SUM(G20:G25)
A28: LIABILITIES & SHAREHOLDERS' EQUITY (الالتزامات وحقوق الملكية)
A29: Bank Overdrafts & Short-term Credit Lines (تسهيلات بنكية قصيرة الأجل) | B29: ST_LOANS | C29: 3800000 | D29: 4500000 | E29: 6200000 | F29: 8900000 | G29: 11200000
A30: Trade and Notes Payable - Subcontractors (أوراق الدفع والمقاولين) | B30: NOTES_PAY | C30: 5120000 | D30: 7300000 | E30: 9800000 | F30: 13500000 | G30: 15790000
A31: Customer Advances & Unearned Float (دفعات مقدمة من العملاء) | B31: CUST_ADV | C31: 38500000 | D31: 48200000 | E31: 72000000 | F31: 95000000 | G31: 117680000
A32: Long-term Bank Debt (قروض بنكية وتسهيلات طويلة الأجل) | B32: LT_DEBT | C32: 8200000 | D32: 9800000 | E32: 14500000 | F32: 19800000 | G32: 26500000
A33: Financial Lease Obligations - Off Balance (التزامات التأجير التمويلي) | B33: LEASE_DEBT | C33: 1200000 | D33: 2100000 | E33: 4800000 | F33: 22100000 | G33: 34400000
A34: Other Liabilities & Provisions (التزامات ومخصصات أخرى) | B34: OTH_LIAB | C34: 2140000 | D34: 2600000 | E34: 3630000 | F34: 4730000 | G34: 6830000
A35: Total Liabilities (إجمالي الالتزامات) | B35: TOT_LIAB | C35: =SUM(C29:C34) | D35: =SUM(D29:D34) | E35: =SUM(E29:E34) | F35: =SUM(F29:F34) | G35: =SUM(G29:G34)
A37: Paid-in Share Capital (رأس المال المصدر والمدفوع) | B37: CAPITAL | C37: 20635600 | D37: 20635600 | E37: 20635600 | F37: 20635600 | G37: 20635600
A38: Legal & General Reserves (احتياطيات وفروق ترجمة) | B38: RESERVES | C38: 3450000 | D38: 4100000 | E38: 5200000 | F38: 7800000 | G38: 11500000
A39: Retained Earnings (أرباح مرحلة ومحتجزة) | B39: RET_EARN | C39: 28654900 | D39: 31164600 | E39: 42454400 | F39: 52834400 | G39: 68164400
A40: Non-Controlling Interests - ADQ ICON (الحصص غير المسيطرة) | B40: NCI_EQ | C40: 0 | D40: 0 | E40: 0 | F40: 33500000 | G40: 59500000
A41: Total Shareholders' Equity (إجمالي حقوق الملكية) | B41: TOT_EQUITY | C41: =SUM(C37:C40) | D41: =SUM(D37:D40) | E41: =SUM(E37:E40) | F41: =SUM(F37:F40) | G41: =SUM(G37:G40)
A42: Total Liabilities & Equity (إجمالي الالتزامات وحقوق الملكية) | B42: TOT_EQ_LIAB | C42: =C35+C41 | D42: =D35+D41 | E42: =E35+E41 | F42: =F35+F41 | G42: =G35+G41
A43: BALANCE CHECK: Assets - (Liab + Equity) (فحص التوازن) | B43: CHECK | C43: =C26-C42 | D43: =D26-D42 | E43: =E26-E42 | F43: =F26-F42 | G43: =G26-G42

Sheet Source & uses analysis 
A1: Talaat Moustafa Group Holding — Source & Uses Analysis (FY2024 vs FY2025)
A2: Tracking Balance Sheet Dynamic Shifts & Liquidity Deployment (Values in EGP '000)
A3: Balance Sheet Line Item / بند الميزانية | B3: At Dec 31, 2024 | C3: At Dec 31, 2025 | D3: Change (التغير) | E3: Source (مصدر نقد) | F3: Use (استخدام سيولة) | G3: Classification
A4: Cash and Cash Equivalents (نقدية وما في حكمها) | B4: ='Financial statement'!F20 | C4: ='Financial statement'!G20 | D4: =C4-B4 | E4: =IF(D4<0, -D4, 0) | F4: =IF(D4>0, D4, 0) | G4: =IF(E4>0, "Source (مصدر)", "Use (استخدام)")
A5: Accounts and Notes Receivable (المدينون وأوراق القبض) | B5: ='Financial statement'!F21 | C5: ='Financial statement'!G21 | D5: =C5-B5 | E5: =IF(D5<0, -D5, 0) | F5: =IF(D5>0, D5, 0) | G5: =IF(E5>0, "Source (مصدر)", "Use (استخدام)")
A6: Real Estate Work in Progress (مشروعات قيد التنفيذ) | B6: ='Financial statement'!F22 | C6: ='Financial statement'!G22 | D6: =C6-B6 | E6: =IF(D6<0, -D6, 0) | F6: =IF(D6>0, D6, 0) | G6: =IF(E6>0, "Source (مصدر)", "Use (استخدام)")
A7: Financial Investments (استثمارات مالية وأذون) | B7: ='Financial statement'!F23 | C7: ='Financial statement'!G23 | D7: =C7-B7 | E7: =IF(D7<0, -D7, 0) | F7: =IF(D7>0, D7, 0) | G7: =IF(E7>0, "Source (مصدر)", "Use (استخدام)")
A8: Fixed Assets & CWIP (أصول ثابتة ومشروعات فنادق) | B8: ='Financial statement'!F24 | C8: ='Financial statement'!G24 | D8: =C8-B8 | E8: =IF(D8<0, -D8, 0) | F8: =IF(D8>0, D8, 0) | G8: =IF(E8>0, "Source (مصدر)", "Use (استخدام)")
A9: Other Assets (أصول أخرى) | B9: ='Financial statement'!F25 | C9: ='Financial statement'!G25 | D9: =C9-B9 | E9: =IF(D9<0, -D9, 0) | F9: =IF(D9>0, D9, 0) | G9: =IF(E9>0, "Source (مصدر)", "Use (استخدام)")
A10: Bank Overdrafts & Short-term Credit Lines (تسهيلات بنكية) | B10: ='Financial statement'!F29 | C10: ='Financial statement'!G29 | D10: =C10-B10 | E10: =IF(D10>0, D10, 0) | F10: =IF(D10<0, -D10, 0) | G10: =IF(E10>0, "Source (مصدر)", "Use (استخدام)")
A11: Trade and Notes Payable (أوراق دفع ومقاولين) | B11: ='Financial statement'!F30 | C11: ='Financial statement'!G30 | D11: =C11-B11 | E11: =IF(D11>0, D11, 0) | F11: =IF(D11<0, -D11, 0) | G11: =IF(E11>0, "Source (مصدر)", "Use (استخدام)")
A12: Customer Advances (دفعات مقدمة من العملاء) | B12: ='Financial statement'!F31 | C12: ='Financial statement'!G31 | D12: =C12-B12 | E12: =IF(D12>0, D12, 0) | F12: =IF(D12<0, -D12, 0) | G12: =IF(E12>0, "Source (مصدر)", "Use (استخدام)")
A13: Long-term Bank Debt (قروض بنكية طويلة الأجل) | B13: ='Financial statement'!F32 | C13: ='Financial statement'!G32 | D13: =C13-B13 | E13: =IF(D13>0, D13, 0) | F13: =IF(D13<0, -D13, 0) | G13: =IF(E13>0, "Source (مصدر)", "Use (استخدام)")
A14: Financial Lease Obligations (التزامات التأجير التمويلي) | B14: ='Financial statement'!F33 | C14: ='Financial statement'!G33 | D14: =C14-B14 | E14: =IF(D14>0, D14, 0) | F14: =IF(D14<0, -D14, 0) | G14: =IF(E14>0, "Source (مصدر)", "Use (استخدام)")
A15: Other Liabilities & Provisions (التزامات ومخصصات أخرى) | B15: ='Financial statement'!F34 | C15: ='Financial statement'!G34 | D15: =C15-B15 | E15: =IF(D15>0, D15, 0) | F15: =IF(D15<0, -D15, 0) | G15: =IF(E15>0, "Source (مصدر)", "Use (استخدام)")
A16: Share Capital (رأس المال المصدر) | B16: ='Financial statement'!F37 | C16: ='Financial statement'!G37 | D16: =C16-B16 | E16: =IF(D16>0, D16, 0) | F16: =IF(D16<0, -D16, 0) | G16: =IF(E16>0, "Source (مصدر)", "Use (استخدام)")
A17: Reserves & Translation Differences (احتياطيات وفروق ترجمة) | B17: ='Financial statement'!F38 | C17: ='Financial statement'!G38 | D17: =C17-B17 | E17: =IF(D17>0, D17, 0) | F17: =IF(D17<0, -D17, 0) | G17: =IF(E17>0, "Source (مصدر)", "Use (استخدام)")
A18: Retained Earnings (أرباح مرحلة محتجزة) | B18: ='Financial statement'!F39 | C18: ='Financial statement'!G39 | D18: =C18-B18 | E18: =IF(D18>0, D18, 0) | F18: =IF(D18<0, -D18, 0) | G18: =IF(E18>0, "Source (مصدر)", "Use (استخدام)")
A19: Non-Controlling Interests / ADQ ICON (حصص غير مسيطرة) | B19: ='Financial statement'!F40 | C19: ='Financial statement'!G40 | D19: =C19-B19 | E19: =IF(D19>0, D19, 0) | F19: =IF(D19<0, -D19, 0) | G19: =IF(E19>0, "Source (مصدر)", "Use (استخدام)")
A20: Total Sources & Uses (إجمالي مصادر واستخدامات الأموال) | E20: =SUM(E4:E19) | F20: =SUM(F4:F19) | G20: =IF(E20=F20, "Balanced ✓ (توازن تام)", "Variance")

Sheet Common size analysis
A1: Talaat Moustafa Group Holding — Vertical Common Size Analysis (FY2023 – FY2025)
A2: Income Statement as % of Total Sales & Balance Sheet as % of Total Assets
A3: Statement Line Item / البند المحاسبي | B3: FY2023 (EGP '000) | C3: % of Base (2023) | D3: FY2024 (EGP '000) | E3: % of Base (2024) | F3: FY2025 (EGP '000) | G3: % of Base (2025)
A4: Sales Revenue (إجمالي الإيرادات) | B4: ='Financial statement'!E4 | C4: =B4/$B$4 | D4: ='Financial statement'!F4 | E4: =D4/$D$4 | F4: ='Financial statement'!G4 | G4: =F4/$F$4
A5: Cost of Goods Sold (تكلفة الإيرادات) | B5: ='Financial statement'!E5 | C5: =B5/$B$4 | D5: ='Financial statement'!F5 | E5: =D5/$D$4 | F5: ='Financial statement'!G5 | G5: =F5/$F$4
A6: Gross Profit (مجمل الربح) | B6: ='Financial statement'!E6 | C6: =B6/$B$4 | D6: ='Financial statement'!F6 | E6: =D6/$D$4 | F6: ='Financial statement'!G6 | G6: =F6/$F$4
A7: Selling, General & Admin (مصروفات إدارية وعمومية) | B7: ='Financial statement'!E7 | C7: =B7/$B$4 | D7: ='Financial statement'!F7 | E7: =D7/$D$4 | F7: ='Financial statement'!G7 | G7: =F7/$F$4
A8: Operating Profit / EBIT (أرباح التشغيل) | B8: ='Financial statement'!E9 | C8: =B8/$B$4 | D8: ='Financial statement'!F9 | E8: =D8/$D$4 | F8: ='Financial statement'!G9 | G8: =F8/$F$4
A9: Finance Costs / Interest (الأعباء التمويلية) | B9: ='Financial statement'!E10 | C9: =B9/$B$4 | D9: ='Financial statement'!F10 | E9: =D9/$D$4 | F9: ='Financial statement'!G10 | G9: =F9/$F$4
A10: Net Profit After Taxes (صافي الربح المجمع) | B10: ='Financial statement'!E15 | C10: =B10/$B$4 | D10: ='Financial statement'!F15 | E10: =D10/$D$4 | F10: ='Financial statement'!G15 | G10: =F10/$F$4

Sheet Ratios & CFO Scorecard
A1: Talaat Moustafa Group Holding — Construction CFO Strategic Ratio Scorecard (FY21 – FY25)
A2: Audited Forensic Metrics: Liquidity, Working Capital Cycles, Off-Balance Leases & Subcontractor Exposure
A3: Metric / Ratio Classification | B3: Target Norm | C3: FY2021 | D3: FY2022 | E3: FY2023 | F3: FY2024 | G3: FY2025
A4: Current Ratio (النسبة الجارية) | B4: 1.2x - 1.5x | C4: 1.54 | D4: 1.58 | E4: 1.49 | F4: 1.54 | G4: 1.63
A5: Quick Ratio (Acid-Test بدون مخزون) | B5: > 0.8x | C5: 0.60 | D5: 0.54 | E5: 0.57 | F5: 0.67 | G5: 0.73
A6: Cash Ratio (نسبة النقدية الفورية) | B6: > 0.2x | C6: 0.09 | D6: 0.08 | E6: 0.13 | F6: 0.27 | G6: 0.28
A7: Days Payable Outstanding - DPO (فترة سداد الموردين) | B7: 60-90 days | C7: — | D7: 134 days | E7: 141 days | F7: 138 days | G7: 160 days
A8: Days Sales Inventory - DSI (فترة دوران المخزون) | B8: 360-720d | C8: 1,659d | D8: 1,490d | E8: 1,372d | F8: 1,194d | G8: 1,214d
A9: Days Sales Outstanding - DSO (فترة تحصيل العملاء) | B9: 90-180d | C9: 582d | D9: 525d | E9: 467d | F9: 375d | G9: 367d
A10: Cash Conversion Cycle - CCC (دورة التحويل النقدي) | B10: — | C10: — | D10: 1,881d | E10: 1,698d | F10: 1,431d | G10: 1,421d
A11: Debt to Equity Ratio (الدين إلى الملكية) | B11: < 1.5x | C11: 1.12 | D11: 1.33 | E11: 1.62 | F11: 1.43 | G11: 1.33
A12: Interest Coverage Ratio - ICR (تغطية الفوائد) | B12: > 3.0x | C12: 4.02x | D12: 3.73x | E12: 3.74x | F12: 3.20x | G12: 3.09x
A13: Off-Balance Financial Leases (التأجير التمويلي) | B13: Minimal | C13: 1.20 B | D13: 2.10 B | E13: 4.80 B | F13: 22.10 B | G13: 34.40 B
A14: Gross Profit Margin (هامش مجمل الربح) | B14: > 30% | C14: 33.0% | D14: 33.2% | E14: 33.3% | F14: 33.2% | G14: 33.4%
... A17: Return on Assets - ROA (العائد على الأصول) | B17: > 3% | C17: 1.59% | D17: 1.71% | E17: 1.85% | F17: 3.27% | G17: 4.89%

Sheet TMG Deep SWOT Matrix
A1: Talaat Moustafa Group Holding — Deep Strategic SWOT Matrix (Audited Corporate Evidence)
A3: ID | B3: SWOT Dimension | C3: Strategic Factor | D3: Detailed Forensic Description | E3: Audited Metric / Evidence | F3: Strategic Moat / Impact
A4: S1 | B4: Strength (قوة) | C4: Dominant Landbank (مخزون أراضٍ سيادي) | D4: Holds Egypt's largest private landbank across East Cairo, North Coast, and Gulf. | E4: 26,722+ Feddans (>112M sqm BUA); Madinaty (8,000 feddans), Noor, SouthMED | F4: High Moat (حاجز تنافسي مطلق)
A5: S2 | B5: Strength (قوة) | C5: Massive Sales Backlog (مبيعات غير مسلمة) | D5: Unprecedented revenue visibility from contracted off-plan unit sales awaiting delivery. | E5: EGP 441.2 Billion Backlog (as of Dec 2025); exceeds EGP 460B in H1 2026 | F5: High Visibility (استقرار تدفقات)
A6: S3 | B6: Strength (قوة) | C6: Headline Earnings Growth (نمو الأرباح) | D6: Record revenue and net profit expansion driven by unit delivery cycles & hotel turnover. | E6: FY25 Revenue EGP 62.5B (+46%), Net Profit EGP 18.2B (+43% YoY) | F6: High Profitability (كفاءة ربحية)
A7: S4 | B7: Strength (قوة) | C7: Hospitality FX Cash Flows (كاش دولاري) | D7: Icon hotel portfolio produces robust USD/EUR earnings hedging group against EGP devaluation. | E7: Hospitality Revenue EGP 14.9B in FY25; 51% acquisition of 7 state historic hotels | F7: FX Hedge Moat (درع تحوط العملة)
A8: S5 | B8: Strength (قوة) | C8: Asset-Light Pivot (تطوير خفيف الأصول) | D8: Shift toward master developer model (SouthMED) capturing fees without land liabilities. | E8: SouthMED (~8% master dev fee) & The Spine NBE JV plot sale EGP 67.12B | F8: Capital Light (تخفيف الأصول)
A9: S6 | B9: Strength (قوة) | C9: Integrated City Utilities (إيرادات دورية) | D9: Captures recurring commercial leasing, utilities, sports clubs, and transportation. | E9: Recurring Revenue EGP 10.9B (+64% YoY); Open Air Mall (260k sqm GLA) | F9: Resilient Cash (إيرادات مستدامة)
A10: W1 | B10: Weakness (ضعف) | C10: Cash Conversion Lag (فجوة تحويل الكاش) | D10: Operating cash flow trails accounting profits due to cash absorption in construction WIP. | E10: H1 2026 OCF EGP 3.11B vs Net Profit EGP 9.95B (~31% conversion); EGP 18.26B WIP burn | F10: Liquidity Drag (استنزاف سيولة)
A11: W2 | B11: Weakness (ضعف) | C11: Off-Balance Lease Debt (تأجير تمويلي) | D11: Sale-and-leaseback transactions create fixed monthly bank debt servicing obligations. | E11: EGP 43.99 Billion Lease Obligations (June 2026), up from EGP 34.4B in Dec 2025 | F11: High Leverage (رافعة ديون خفية)
A12: W3 | B12: Weakness (ضعف) | C12: High Interest Burn (أعباء الفوائد) | D12: Elevated domestic interest rates on borrowings erode gross operating profits. | E12: Finance Expense EGP 4.56B in FY25 (7.3% of revenue); Central Bank corridor > 27% | F12: Margin Erosion (تآكل هوامش الربح)
A13: W4 | B13: Weakness (ضعف) | C13: Subcontractor Payment Stretch (تمديد DPO) | D13: Aggressive working capital policy forces contractors to finance works via deferred paper. | E13: DPO extended to 160 days in FY25; Notes payable climbed to EGP 15.79B | F13: Supply Chain Strain (خطر المقاولين)
A14: W5 | B14: Weakness (ضعف) | C14: Key-Person Concentration (المركزية المفرطة) | D14: Concentration of strategic decisions and financial approvals in executive leadership. | E14: Centralized approval hierarchy slowing payment certifications and dispute resolution | F14: Governance Bottleneck (اختناق إداري)
... A27: T6 | B27: Threat (تهديد) | C27: Regulatory Crackdown on Fees (حماية المستهلك) | D27: Enforcement of CPA Article 15 barring developer fees on unit resales (5%-10%). | E27: Legal risk of contract voiding and fines regarding transfer fee revenue streams | F27: Compliance Risk (مخاطر إلغاء رسوم التنازل)

Sheet Strategic TOWS Roadmap
A1: Talaat Moustafa Group Holding — Strategic TOWS Action Matrix (Executive Roadmap)
A3: Strategy ID | B3: TOWS Strategy Posture | C3: Corporate Strategy & Action | D3: Detailed Operational Implementation Roadmap | E3: Priority | F3: Subcontractor / Partner Implication
A4: SO-1 | B4: SO (Maxi-Maxi) | C4: Leverage Landbank for Asset-Light Growth | D4: Combine massive 26k+ feddan landbank with master development fee model (SouthMED) to maximize cash generation while minimizing balance sheet risk. | E4: High Priority | F4: Unlocks multi-billion EGP infrastructure, lake, and pool subcontracting packages.
A5: SO-2 | B5: SO (Maxi-Maxi) | C5: Monetize Icon Hotel FX Cash Flows | D5: Deploy USD/EUR hospitality revenues from Four Seasons/Historic hotels to fund cross-border regional expansion in KSA (Banan) and Oman (Jood). | E5: High Priority | F5: TMG possesses abundant USD liquidity in offshore/hotel arms but keeps it segregated.
A6: SO-3 | B6: SO (Maxi-Maxi) | C6: Scale Commercial Leasing Portfolio | D6: Utilize EGP 441B backlog visibility to pre-lease commercial retail hubs (Open Air Mall, East Hub) and expand recurring revenue base. | E6: Medium Priority | F6: Steady recurring cash streams strengthen developer balance sheet long-term.
A7: ST-1 | B7: ST (Maxi-Mini) | C7: Centralized Bulk Material Hedging | D7: Use group financial scale and liquidity reserves (EGP 66.4B) to bulk-purchase rebar and cement directly, bypassing subcontractor inflation markups. | E7: High Priority | F7: TMG strips material supply margin from contractors, turning them into pure labor/MEP installers.
A8: ST-2 | B8: ST (Maxi-Mini) | C8: FX Debt & Revenue Matching | D8: Align foreign currency debt service obligations with USD hospitality earnings, shielding group balance sheet from EGP devaluation shocks. | E8: High Priority | F8: Isolates hotel assets while real estate operations absorb local inflation.
A9: ST-3 | B9: ST (Maxi-Mini) | C9: Flexible Customer Financing | D9: Utilize strong balance sheet to extend unit payment plans to 10-12 years, sustaining sales velocity amidst domestic affordability strain. | E9: Medium Priority | F9: Stretches collection cycle; increases reliance on contractor working capital float.
A10: WO-1 | B10: WO (Mini-Maxi) | C10: Refinance High-Cost EGP Debt | D10: Use sovereign wealth partnerships (ADQ/ADNEC) and Gulf expansion cash flows to substitute 28.6% EGP debt with lower-cost regional credit. | E10: High Priority | F10: Reduces interest burn (currently EGP 4.56B), releasing cash flow for site execution.
A11: WO-2 | B11: WO (Mini-Maxi) | C11: Accelerate Cash Conversion via Asset Monetization | D11: Convert properties under development into liquid cash by monetizing commercial spaces via Rawasy and leasing vehicles to close OCF gap. | E11: High Priority | F11: Securitization injections provide non-recourse liquidity for ongoing construction.
A12: WO-3 | B12: WO (Mini-Maxi) | C12: Enhance Maintenance Reserve Governance | D12: Establish independent audited trust accounts for Madinaty/Rehab maintenance deposits to eliminate resident litigation and restore brand trust. | E12: Medium Priority | F12: Resolves legal drag and prevents court attachment on developer bank accounts.
A13: WT-1 | B13: WT (Mini-Mini) | C13: Shorten Subcontractor Payment Cycles | D13: Reduce post-dated check tenors from 270 days to 60-90 days to prevent trade subcontractor insolvency and avoid project completion slippages. | E13: Critical Priority | F13: DIRECT MITIGATION: TMG must accelerate cash disbursements to prevent critical MEP collapse.
A14: WT-2 | B14: WT (Mini-Mini) | C14: Reform Resale Fee Structures | D14: Replace percentage-based resale transfer fees with flat administrative costs to comply with CPA Article 15 and eliminate legal liability. | E14: High Priority | F14: Shields executive leadership from misdemeanor court penalties under CPA law.
A15: WT-3 | B15: WT (Mini-Mini) | C15: Cap Off-Balance Sheet Lease Leverage | D15: Freeze new sale-and-leaseback transactions (currently EGP 44B) to ensure debt service obligations do not consume operating cash flows. | E15: High Priority | F15: Protects operational cash flow; prevents institutional leasing debt from starving site payments.

Sheet P.ZONE Subcontractor Model
A1: P.ZONE INTERNATIONAL — Financial Exposure & Subcontractor Defense Model (TMG Water Packages)
A2: Water Features, Swimming Pools, Artificial Lakes & Electro-Mechanical (MEP) Risk Assessment
A3: Parameter / Scenario Variable | B3: 50M EGP Standard Package | C3: 100M EGP Mega Lake Package | D3: 20M EGP Boutique Pool Package | E3: Calculation Formula | F3: Forensic Implication for P.ZONE
A4: Total Contract Value (قيمة العقد) | B4: 50,000,000 ج.م | C4: 100,000,000 ج.م | D4: 20,000,000 ج.م | E4: Contract Lump Sum | F4: Target Subcontract Package Scope
A5: Imported MEP Equipment % (نسبة المستورد دولاري) | B5: 65.0% | C5: 70.0% | D5: 55.0% | E5: Pumps, Filtration, Liners, Chemical Dosing | F5: Paid 100% Cash in USD to Foreign Suppliers
A6: Imported USD Value (قيمة المستورد بالدولار) | B6: $656,566 | C6: $1,414,141 | D6: $222,222 | E6: Contract Value * MEP % / 49.5 | F6: Immediate Cash Outflow Required by P.ZONE
A7: Local Civil & Labor Cost (الأعمال المدنية والعمالة) | B7: 17,500,000 ج.م | C7: 30,000,000 ج.م | D7: 9,000,000 ج.م | E7: Contract Value * (1 - MEP %) | F7: Local EGP working capital requirements
A8: Expected Payment Delay (متوسط تأخير المستخلص) | B8: 160 Days (DPO) | C8: 180 Days (DPO) | D8: 135 Days (DPO) | E8: TMG Audited DPO Average | F8: Stretches to 270 days with post-dated checks
A9: Required Frozen Working Capital (الكاش المجمد) | B9: 17,534,246 ج.م | C9: 39,452,055 ج.م | D9: 5,917,808 ج.م | E9: Contract * (Delay / 365) * 0.80 | F9: Liquid capital P.ZONE must self-finance
A10: Bank Financing Cost @ 28% APR (تكلفة الفائدة البنكية) | B10: 2,151,889 ج.م | C10: 5,446,950 ج.م | D10: 612,492 ج.م | E10: Frozen Capital * 28% * (Delay / 365) | F10: Directly erodes 4.3% - 5.4% of contract profit
A11: Unhedged FX Devaluation Loss @ 15% (خسارة التعويم) | B11: 4,875,000 ج.م | C11: 10,500,000 ج.م | D11: 1,650,000 ج.م | E11: Imported MEP Value * 15% Deval | F11: Destroys full margin if contract not USD-pegged
A12: Total Financial Exposure (إجمالي المخاطرة النقدية) | B12: 7,026,889 ج.م | C12: 15,946,950 ج.م | D12: 2,262,492 ج.م | E12: Interest Cost + FX Deval Loss | F12: Exceeds standard 15%-20% contractor net profit!
A13: Minimum Required Mobilization Advance (الدفعة المقدمة) | B13: 20,000,000 ج.م (40%) | C13: 45,000,000 ج.م (45%) | D13: 7,000,000 ج.م (35%) | E13: Max(35%, MEP % * 60%) | F13: MANDATORY: Must cover 100% of imported equipment LCs
A14: Subcontract Risk Verdict (التقييم الجنائي النهائي) | B14: CRITICAL (خطر حرج) | C14: SEVERE (خطر شديد جداً) | D14: HIGH (خطر مرتفع) | E14: Risk Assessment Rule | F14: DO NOT SIGN without advance LC & elimination of Back-to-Back
