Workbook

Sheet دليل إدارة المخاطر للمهندس
A1: 🏗️ دليل مهندس إدارة المشروعات والمكتب الفني (Project Controls & Risk Engineering Guide)
A3: 📌 أولاً: المفهوم الهندسي لإدارة المخاطر في المشروعات العملاقة (Megaprojects):
A4: يا بشمهندس، بصفتك مهندس في مشروع ضخم (زي مدينتي أو ساوث ميد أو مدينة نور)، إدارة المخاطر (Risk Management) مش مجرد كلام نظري أو جدول بنسلمه في كراسة الشروط. إدارة المخاطر هي 'نظام إنذار مبكر' (Early Warning System) بيجاوبك بالأرقام على 3 أسئلة حاسمة: 1. إيه الأعطال والمشاكل التعاقدية والتنفيذية المتكررة في الموقع؟ (Disputes, Late IPCs, Inflation, Labor Strife). 2. إيه احتمالية حدوث المشكلة دي إحصائياً؟ ومعدل تكرارها كل أسبوع؟ 3. مين الخطر الأكبر اللي لو مخدناش بالنا منه فوراً، هيوقف الجداول الزمنية (Baseline Schedule) ويستنزف ميزانية المشروع (Cost Overrun)؟
A6: 📑 ثانياً: الهيكل الإجرائي لصفحات الملف (Workflow Architecture):
A7: الملف ده مبني على تسلسل هندسي واحترافي مقسم لـ 4 مراحل متتابعة: 1. ورقة العصف الذهني (Risk Brainstorming): تحديد المخاطر المرتبطة بكل إدارة (Technical Office, Procurement, Site Ops, Legal) وطرق التحكم الوقائية. 2. شيتات التقييم الدوري الأسبوعي (Risk Assesment): رصد وتتبع عدد مرات ظهور المشكلة (Occurrences) أسبوعياً على مدار 12 أسبوعاً (3 أشهر) واستخراج معامل التشتت (Likelihood L عبر AVEDEV). 3. شيتات نمذجة وايبول (Weibull Reliability Analysis): تطبيق نموذج توزيع وايبول الرياضي لحساب معدل الإخفاق الزمني (Hazard Rate) واشتقاق الاحتمالية التراكمية (p). 4. مصفوفة الأولوية والترتيب النهائي (Risk score): حساب درجة الخطر الإجمالية (Risk Score = p × L) لترتيب الأولويات للمدير التنفيذي ومدير المشروع.
A9: 📐 ثالثاً: الدليل الرياضي لمعادلات وايبول (Weibull Analysis Explained for Engineers):
A10: توزيع وايبول (Weibull Distribution) هو النموذج الإحصائي الأقوى عالمياً في هندسة الموثوقية (Reliability Engineering) وإدارة مخاطر التشييد: • معامل الشكل (Weibull Slope α): بيعبر عن سلوك الخطر مع الوقت: - إذا كان α > 1 (زي ما طالع في ملفنا 2.0 إلى 2.7): ده بيثبت هندسياً ظاهرة 'معدل التآكل المتسارع' (Wear-out Phase)؛ يعني المشكلة كل ما الوقت بيعدي عليها من غير حل جذري، بتتراكم وتتفاقم وتضغط على مقاولي الباطن بمعدل أسرع! • معامل القياس (Scale Parameter β): بيعبر عن الزمن المعتاد المميز لتكرار الواقعة (Characteristic Life). • دالة الاحتمال التراكمي (Weibull CDF p): الاحتمالية الفعلية لحدوث الخطر عند وصول المشروع لمتوسط تردد التشغيل المعتاد. • حدود التحكم عند مستوى ثقة 99% (Action Limit): ده السقف الحرج (Threshold). لو عدد المشاكل في أي أسبوع تجاوز هذا الرقم، يبقى النظام خرج عن السيطرة الإحصائية (Out-of-Control) ولازم تتدخل كمهندس فوراً وتصدر تقرير عدم مطابقة أو مذكرة للمدير العام.
A12: 🏢 رابعاً: مصفوفة المخاطر الأربعة المدققة لمجموعة طلعت مصطفى (TMG Specific Risks):
A13: 🥇 المركز الأول (Rank 1) — تأخير صرف المستخلصات وأوراق الدفع (Payment & Privity Shield): توقيع العقود مع الذراع التنفيذي (شركة الإسكندرية ACC أو أتريوم AQC) وليس القابضة، ومد أجل الاعتماد عبر 7 بوابات حصر، ثم السداد بشيكات آجلة (PDCs) لـ 90-270 يوماً. حجم أوراق الدفع يتجاوز 15.79B جنيه، وهو الخطر الأول لأنه بيهدد السيولة النقدية لمقاولي الباطن. 🥈 المركز الثاني (Rank 2) — تضخم الأسعار وفصل التوريد عن المصنعيات (Cost Inflation & Material Decoupling): شراء الخامات الأساسية (حديد وأسمنت) مركزياً وحصر المقاول على المصنعيات، مما يجرده من هوامش أرباح التوريد ويعرضه لزيادات أجور العمالة والمعدات. 🥉 المركز الثالث (Rank 3) — مكون الأعمال الكهروميكانيكية ومعدات البحيرات المستوردة (Water & Lagoon MEP): تنفيذ 107 كم بحيرات وشواطئ بمشروعات ساوث ميد ومدينتي يتطلب استيراد محطات ضخ وفلاتر متطورة بالدولار واليورو، مما يعرض التكلفة لفروق سعر الصرف وتأخير التوريد الجمركي. 🎖️ المركز الرابع (Rank 4) — علاقات العمل واحتجاجات الموقع (Labor Strife & Workforce Friction): مخاطر توقف العمالة بالمواقع الكبرى حال تعثر المقاول في سداد الأجور، وتستوجب تفعيل حساب وسيط (Escrow) لصرف مستحقات العمالة مباشرة.

Sheet Risk Brainstorming
C1: TMG Holding & Subcontractors — Master Forensic Risk Taxonomy
A3: Department | B3: Key Elements | C3: Construction Processes / Risk Factors | D3: Identified Forensic Risks | E3: Current Risk Management Methods (Observed) | F3: Proposed Forensic Controls & Safeguards
A4: Commercial & Legal Controls | B4: Subcontractor IPCs & Privity | C4: 7-Gate Quantity Audit, PDC Issuance (90-270d), ACC/Atrium Privity Ring-Fencing | D4: Prolonged payment certification cycles (135–270d) & commercial paper (>EGP 15.79B) creating subcontractor insolvency | E4: Multi-tier site quantity survey, central Dokki audit, deferred post-dated checks (PDC), mandatory CRCICA arbitration | F4: Statutory prompt payment escrow, strict 45-day IPC sign-off limit, carve-out for Economic Court fast-track recovery
A5: Procurement & Cost Control | B5: Bulk Supply vs Labor Subcontract | C5: Centralized Steel/Cement Procurement, Labor-only Subcontracts, Currency Devaluation | D5: Subcontractor margin erosion & contractor abandonment due to soaring labor wages & unindexed fixed-rate BOQs | E5: Direct bulk buying from Ezz/Beshay/Suez, lump-sum labor pricing without price adjustment clauses | F5: Contractual price escalation formulas linked to CAPMAS Producer Price Index & Ministry of Housing monthly bulletins
A6: Specialized Infrastructure & MEP | B6: Artificial Lagoons & Pumping | C6: 107km Shoreline/Lagoons (SouthMED/Madinaty), High-Spec Filtration, Imported Pumps/Nozzles | D6: Foreign exchange rate escalation (USD/EUR) on imported MEP electro-mechanical equipment & lifecycle maintenance deficits | E6: Tiered subcontractor assignment (P.Zone/Metito), milestone-linked advance payments | F6: FX hedging buffer reserves, local component assembly (e.g. Schindler JV model), life-cycle maintenance sinking funds
A7: Site Operations & HSE | B7: Subcontractor Labor & Execution | C7: Mega-site Mobilization (Madinaty, Noor, SouthMED), Labor Camp Management, Subcontractor Payroll | D7: Work stoppages, labor strikes, and police/regulatory intervention stemming from delayed subcontractor payroll | E7: Site security, security clearances, ad-hoc contractor reconciliation meetings | F7: Dedicated direct-labor escrow account, biometric workforce verification, independent worker grievance hotline
A9: 📘 توجيه هندسي: هيكلية العصف الذهني وتبويب المخاطر التعاقدية (Risk Breakdown Structure):
A10: • الهدف الهندسي: قبل إصدار أوامر الإسناد (LOA) وبدء أعمال الموقع، بنعمل فحص شامل لكل إدارة لتحديد مسارات النزاع المحتملة. • الأعمدة 1 و 2 (Department & Key Elements): تحديد الإدارة المعنية ومحور العمليات التخصصي (عقود، مشتريات، إشراف موقع، أو بنية تحتية). • العمود 3 و 4 (Processes & Identified Risks): وصف الآلية التشغيلية التي ينشأ منها الخطر، والتعريف الفني للخطر المترتب عليها (مثل تأخر صرف مستخلصات مقاولي الباطن IPCs أو تآكل هوامش الربح نتيجة التضخم). • العمود 5 و 6 (Current vs Proposed Controls): مقارنة أسلوب إدارة المشروع الحالي بالضوابط التعاقدية الموصى بها لإغلاق ثغرات النزاع والتحوط ضد قضايا التحكيم أو المطالبات الزمنية والمالية (Claims & EOT).

Sheet Risk Assesment(Payment&Privity)
E1: Severity Of Risk (Scale 1 to 5)
A2: Period | B2: Week | C2: Key Elements | D2: Risk | E2: 1 | F2: 2 | G2: 3 | H2: 4 | I2: 5 | J2: Number of occuraneces | K2: Likelihood
A3: M1 | B3: Week 1 | C3: Subcontractor IPCs & Privity | D3: Prolonged payment certification cycles (135–270d) & commercial paper (>EGP 15.79B) creating subcontractor insolvency | J3: 8 | K3: =J3/J$15
B4: Week 2 | J4: 12 | K4: =J4/J$15
B5: Week 3 | J5: 11 | K5: =J5/J$15
B6: Week 4 | J6: 7 | K6: =J6/J$15
A7: M2 | B7: Week 1 | J7: 9 | K7: =J7/J$15
B8: Week 2 | J8: 6 | K8: =J8/J$15
B9: Week 3 | J9: 14 | K9: =J9/J$15
B10: Week 4 | J10: 15 | K10: =J10/J$15
A11: M3 | B11: Week 1 | J11: 12 | K11: =J11/J$15
B12: Week 2 | J12: 16 | K12: =J12/J$15
B13: Week 3 | J13: 10 | K13: =J13/J$15
B14: Week 4 | J14: 13 | K14: =J14/J$15
I15: Total / Disp: | J15: =SUM(J3:J14) | K15: =AVEDEV(K3:K14)
A17: 📘 التوجيه الهندسي لقراءة السجل: سجل الرصد الأسبوعي لمستخلصات مقاولي الباطن والعزل التعاقدي (Payment Certification & Privity Audit)
A18: • السياق الهندسي: رصد وتوثيق دوري لشكاوى ومطالبات مقاولي الباطن بشأن تأخر اعتماد المستخلصات الجارية (IPCs) والشيكات الآجلة (PDCs) لدى شركة الإسكندرية (ACC) وأتريوم (AQC). • عمود عدد التكرارات (Column J - Occurrences): عدد وقائع النزاع أو الشكاوى أو مذكرات التأخير المسجلة رسمياً خلال كل أسبوع تعاقدي. • عمود الاحتمالية النسبية (Column K - Relative Likelihood): النسبة المئوية للمشكلة في ذلك الأسبوع مقارنة بإجمالي الوقائع المسجلة خلال الربع السنوي (J/Total). • خلية التشتت الإحصائي (Cell K15 - AVEDEV): حساب متوسط الانحراف المطلق (Average Absolute Deviation). رياضياً: الرقم ده بيقيس مدى تذبذب واستقرار معدل حدوث المشكلة أسبوعياً، وبيشكل مدخل معامل الاحتمالية (Likelihood L) في التقييم النهائي.

Sheet Weibull(Payment & Privity)
B2: Weibull Reliability & Occurrence Modelling: Payment Gatekeeping & Privity
C7: X | D7: Step1 | E7: Step2 | F7: Step3
B8: Weeks | C8: Number of occurances | D8: Rank | E8: X-axis | F8: Y-axis | I8: Excel Weibull function | J8: Parameter / Value | K8: Calculation Step | M8: Statistical Metrics
A9: M1 | B9: Week1 | C9: ='Risk Assesment(Payment&Privity)'!J3 | D9: =RANK(C9,C$9:C$20,1) | E9: =LN(LN(1/(1-((D9-0.3)/(12+0.4))))) | F9: =LN(C9) | I9: Weibull Slope α | J9: =1/SLOPE(F9:F20,E9:E20) | K9: Step4
B10: Week2 | C10: ='Risk Assesment(Payment&Privity)'!J4 | D10: =RANK(C10,C$9:C$20,1) | E10: =LN(LN(1/(1-((D10-0.3)/(12+0.4))))) | F10: =LN(C10) | I10: Scale Parameter β | J10: =EXP(INTERCEPT(F9:F20,E9:E20)) | K10: Step5 | M10: Mean (average)
B11: Week3 | C11: ='Risk Assesment(Payment&Privity)'!J5 | D11: =RANK(C11,C$9:C$20,1) | E11: =LN(LN(1/(1-((D11-0.3)/(12+0.4))))) | F11: =LN(C11) | I11: Weibull, CDF (Cumulative P) | J11: =1-EXP(-((M11/J10)^J9)) | K11: Step6 | M11: =AVERAGE(C9:C20)
B12: Week4 | C12: ='Risk Assesment(Payment&Privity)'!J6 | D12: =RANK(C12,C$9:C$20,1) | E12: =LN(LN(1/(1-((D12-0.3)/(12+0.4))))) | F12: =LN(C12)
A13: M2 | B13: Week5 | C13: ='Risk Assesment(Payment&Privity)'!J7 | D13: =RANK(C13,C$9:C$20,1) | E13: =LN(LN(1/(1-((D13-0.3)/(12+0.4))))) | F13: =LN(C13)
B14: Week6 | C14: ='Risk Assesment(Payment&Privity)'!J8 | D14: =RANK(C14,C$9:C$20,1) | E14: =LN(LN(1/(1-((D14-0.3)/(12+0.4))))) | F14: =LN(C14) | I14: Weibull (CDF) defines cumulative probability of risk occurrence at mean operating frequency
B15: Week7 | C15: ='Risk Assesment(Payment&Privity)'!J9 | D15: =RANK(C15,C$9:C$20,1) | E15: =LN(LN(1/(1-((D15-0.3)/(12+0.4))))) | F15: =LN(C15)
B16: Week8 | C16: ='Risk Assesment(Payment&Privity)'!J10 | D16: =RANK(C16,C$9:C$20,1) | E16: =LN(LN(1/(1-((D16-0.3)/(12+0.4))))) | F16: =LN(C16)
A17: M3 | B17: Week9 | C17: ='Risk Assesment(Payment&Privity)'!J11 | D17: =RANK(C17,C$9:C$20,1) | E17: =LN(LN(1/(1-((D17-0.3)/(12+0.4))))) | F17: =LN(C17)
B18: Week10 | C18: ='Risk Assesment(Payment&Privity)'!J12 | D18: =RANK(C18,C$9:C$20,1) | E18: =LN(LN(1/(1-((D18-0.3)/(12+0.4))))) | F18: =LN(C18)
B19: Week11 | C19: ='Risk Assesment(Payment&Privity)'!J13 | D19: =RANK(C19,C$9:C$20,1) | E19: =LN(LN(1/(1-((D19-0.3)/(12+0.4))))) | F19: =LN(C19)
B20: Week12 | C20: ='Risk Assesment(Payment&Privity)'!J14 | D20: =RANK(C20,C$9:C$20,1) | E20: =LN(LN(1/(1-((D20-0.3)/(12+0.4))))) | F20: =LN(C20)
B21: EXPECTED | C21: =C23
B23: Expected Number of occurances using Weibull | C23: =EXP(((LN(-LN(1-88%)))/(J9))+(LN(J10)))
B24: Expected Number of occurances using Exponential | C24: =LN(1-75%)/(-1/M11)
B26: Standard Deviation | C26: =STDEVP(C9:C20)
B27: Action Limit (99%) | C27: =C23+(NORMSDIST(0.99)*(C26/SQRT(12)))
B28: Normal Limit (99%) | C28: =C23-(NORMSDIST(0.99)*(C26/SQRT(12)))
B30: 📐 دليل المهندس لتحليل نتائج ومؤشرات وايبول الإحصائية (النمذجة الرياضية لموثوقية دورة الصرف ومخاطر السيولة لمقاولي الباطن):
B31: 1. التحويل الخطي لمخطط وايبول (Linearized Plot X & Y): - تم تحويل دالة التوزيع التراكمي إلى معادلة خط مستقيم (Y = ln(C) مقابل X = ln(ln(1/(1-F)))) لتمكين استخراج الميل ونقطة التقاطع عبر دوال SLOPE و INTERCEPT. 2. معامل الشكل ومعدل الإخفاق (Weibull Slope α = 1/SLOPE): - القيمة المحسوبة (α > 1) تؤكد هندسياً أن الخطر يمر بمرحلة 'الإخفاق المتسارع الناتج عن التقادم والضغط المستمر' (Wear-out failure rate). تراكم مستحقات المقاولين أو تأخر التوريد بيزيد من احتمالية توقف الأعمال بمعدل تصاعدي وليس عشوائياً. 3. معامل القياس المميز (Scale Parameter β = EXP(INTERCEPT)): - يمثل التردد المعتاد الذي يصل عنده الخطر لاحتمالية تراكمية تبلغ 63.2%. 4. الاحتمالية التراكمية عند متوسط التشغيل (Weibull CDF p): - النسبة المئوية الدقيقة لاحتمالية تحقق الخطر عند وصول المشروع لمتوسط تردد الحوادث الأسبوعي (Mean M11)، وتستخدم كمدخل أساسي لحساب درجة الخطر الكلية (Probability p). 5. حدود الضبط والتحكم الإحصائي (Action Limit @ 99% Confidence): - محسوبة وفق مبادئ الإحصاء الهندسي (μ + Z * σ / √N). إذا سجل أي أسبوع عدداً من الوقائع يتجاوز حد الإجراء (Action Limit)، فإن النظام يعتبر في حالة 'شذوذ تشغيلي حرج' (Process Out of Control) يفرض رفع تقرير عاجل للإدارة التنفيذية.

Sheet Risk Assesment(Cost Inflation)
E1: Severity Of Risk (Scale 1 to 5)
A2: Period | B2: Week | C2: Key Elements | D2: Risk | E2: 1 | F2: 2 | G2: 3 | H2: 4 | I2: 5 | J2: Number of occuraneces | K2: Likelihood
A3: M1 | B3: Week 1 | C3: Bulk Supply vs Labor Subcontract | D3: Subcontractor margin erosion & contractor abandonment due to soaring labor wages & unindexed fixed-rate BOQs | J3: 10 | K3: =J3/J$15
B4: Week 2 | J4: 14 | K4: =J4/J$15
B5: Week 3 | J5: 9 | K5: =J5/J$15
B6: Week 4 | J6: 12 | K6: =J6/J$15
A7: M2 | B7: Week 1 | J7: 11 | K7: =J7/J$15
B8: Week 2 | J8: 8 | K8: =J8/J$15
B9: Week 3 | J9: 15 | K9: =J9/J$15
B10: Week 4 | J10: 13 | K10: =J10/J$15
A11: M3 | B11: Week 1 | J11: 16 | K11: =J11/J$15
B12: Week 2 | J12: 12 | K12: =J12/J$15
B13: Week 3 | J13: 14 | K13: =J13/J$15
B14: Week 4 | J14: 11 | K14: =J14/J$15
I15: Total / Disp: | J15: =SUM(J3:J14) | K15: =AVEDEV(K3:K14)
A17: 📘 التوجيه الهندسي لقراءة السجل: سجل الرصد الأسبوعي لمطالبات فروق الأسعار وتضخم الخامات (Cost Inflation & Price Variations)
A18: • السياق الهندسي: رصد أسبوعي لطلبات مقاولي الباطن بتعديل أسعار الفئات (Rate Adjustments) نتيجة تضخم أجور العمالة وتكاليف تشغيل المعدات في ظل عقود المصنعيات محددة السعر. • عمود عدد التكرارات (Column J - Occurrences): عدد وقائع النزاع أو الشكاوى أو مذكرات التأخير المسجلة رسمياً خلال كل أسبوع تعاقدي. • عمود الاحتمالية النسبية (Column K - Relative Likelihood): النسبة المئوية للمشكلة في ذلك الأسبوع مقارنة بإجمالي الوقائع المسجلة خلال الربع السنوي (J/Total). • خلية التشتت الإحصائي (Cell K15 - AVEDEV): حساب متوسط الانحراف المطلق (Average Absolute Deviation). رياضياً: الرقم ده بيقيس مدى تذبذب واستقرار معدل حدوث المشكلة أسبوعياً، وبيشكل مدخل معامل الاحتمالية (Likelihood L) في التقييم النهائي.

Sheet Weibull(Cost Inflation)
B2: Weibull Reliability & Occurrence Modelling: Cost Inflation & Decoupling
C7: X | D7: Step1 | E7: Step2 | F7: Step3
B8: Weeks | C8: Number of occurances | D8: Rank | E8: X-axis | F8: Y-axis | I8: Excel Weibull function | J8: Parameter / Value | K8: Calculation Step | M8: Statistical Metrics
A9: M1 | B9: Week1 | C9: ='Risk Assesment(Cost Inflation)'!J3 | D9: =RANK(C9,C$9:C$20,1) | E9: =LN(LN(1/(1-((D9-0.3)/(12+0.4))))) | F9: =LN(C9) | I9: Weibull Slope α | J9: =1/SLOPE(F9:F20,E9:E20) | K9: Step4
B10: Week2 | C10: ='Risk Assesment(Cost Inflation)'!J4 | D10: =RANK(C10,C$9:C$20,1) | E10: =LN(LN(1/(1-((D10-0.3)/(12+0.4))))) | F10: =LN(C10) | I10: Scale Parameter β | J10: =EXP(INTERCEPT(F9:F20,E9:E20)) | K10: Step5 | M10: Mean (average)
B11: Week3 | C11: ='Risk Assesment(Cost Inflation)'!J5 | D11: =RANK(C11,C$9:C$20,1) | E11: =LN(LN(1/(1-((D11-0.3)/(12+0.4))))) | F11: =LN(C11) | I11: Weibull, CDF (Cumulative P) | J11: =1-EXP(-((M11/J10)^J9)) | K11: Step6 | M11: =AVERAGE(C9:C20)
B12: Week4 | C12: ='Risk Assesment(Cost Inflation)'!J6 | D12: =RANK(C12,C$9:C$20,1) | E12: =LN(LN(1/(1-((D12-0.3)/(12+0.4))))) | F12: =LN(C12)
A13: M2 | B13: Week5 | C13: ='Risk Assesment(Cost Inflation)'!J7 | D13: =RANK(C13,C$9:C$20,1) | E13: =LN(LN(1/(1-((D13-0.3)/(12+0.4))))) | F13: =LN(C13)
B14: Week6 | C14: ='Risk Assesment(Cost Inflation)'!J8 | D14: =RANK(C14,C$9:C$20,1) | E14: =LN(LN(1/(1-((D14-0.3)/(12+0.4))))) | F14: =LN(C14) | I14: Weibull (CDF) defines cumulative probability of risk occurrence at mean operating frequency
B15: Week7 | C15: ='Risk Assesment(Cost Inflation)'!J9 | D15: =RANK(C15,C$9:C$20,1) | E15: =LN(LN(1/(1-((D15-0.3)/(12+0.4))))) | F15: =LN(C15)
B16: Week8 | C16: ='Risk Assesment(Cost Inflation)'!J10 | D16: =RANK(C16,C$9:C$20,1) | E16: =LN(LN(1/(1-((D16-0.3)/(12+0.4))))) | F16: =LN(C16)
A17: M3 | B17: Week9 | C17: ='Risk Assesment(Cost Inflation)'!J11 | D17: =RANK(C17,C$9:C$20,1) | E17: =LN(LN(1/(1-((D17-0.3)/(12+0.4))))) | F17: =LN(C17)
B18: Week10 | C18: ='Risk Assesment(Cost Inflation)'!J12 | D18: =RANK(C18,C$9:C$20,1) | E18: =LN(LN(1/(1-((D18-0.3)/(12+0.4))))) | F18: =LN(C18)
B19: Week11 | C19: ='Risk Assesment(Cost Inflation)'!J13 | D19: =RANK(C19,C$9:C$20,1) | E19: =LN(LN(1/(1-((D19-0.3)/(12+0.4))))) | F19: =LN(C19)
B20: Week12 | C20: ='Risk Assesment(Cost Inflation)'!J14 | D20: =RANK(C20,C$9:C$20,1) | E20: =LN(LN(1/(1-((D20-0.3)/(12+0.4))))) | F20: =LN(C20)
B21: EXPECTED | C21: =C23
B23: Expected Number of occurances using Weibull | C23: =EXP(((LN(-LN(1-85%)))/(J9))+(LN(J10)))
B24: Expected Number of occurances using Exponential | C24: =LN(1-75%)/(-1/M11)
B26: Standard Deviation | C26: =STDEVP(C9:C20)
B27: Action Limit (99%) | C27: =C23+(NORMSDIST(0.99)*(C26/SQRT(12)))
B28: Normal Limit (99%) | C28: =C23-(NORMSDIST(0.99)*(C26/SQRT(12)))
B30: 📐 دليل المهندس لتحليل نتائج ومؤشرات وايبول الإحصائية (النمذجة الرياضية لموثوقية التكاليف وحساسية المشروعات لتقلبات التضخم):
B31: 1. التحويل الخطي لمخطط وايبول (Linearized Plot X & Y): - تم تحويل دالة التوزيع التراكمي إلى معادلة خط مستقيم (Y = ln(C) مقابل X = ln(ln(1/(1-F)))) لتمكين استخراج الميل ونقطة التقاطع عبر دوال SLOPE و INTERCEPT. 2. معامل الشكل ومعدل الإخفاق (Weibull Slope α = 1/SLOPE): - القيمة المحسوبة (α > 1) تؤكد هندسياً أن الخطر يمر بمرحلة 'الإخفاق المتسارع الناتج عن التقادم والضغط المستمر' (Wear-out failure rate). تراكم مستحقات المقاولين أو تأخر التوريد بيزيد من احتمالية توقف الأعمال بمعدل تصاعدي وليس عشوائياً. 3. معامل القياس المميز (Scale Parameter β = EXP(INTERCEPT)): - يمثل التردد المعتاد الذي يصل عنده الخطر لاحتمالية تراكمية تبلغ 63.2%. 4. الاحتمالية التراكمية عند متوسط التشغيل (Weibull CDF p): - النسبة المئوية الدقيقة لاحتمالية تحقق الخطر عند وصول المشروع لمتوسط تردد الحوادث الأسبوعي (Mean M11)، وتستخدم كمدخل أساسي لحساب درجة الخطر الكلية (Probability p). 5. حدود الضبط والتحكم الإحصائي (Action Limit @ 99% Confidence): - محسوبة وفق مبادئ الإحصاء الهندسي (μ + Z * σ / √N). إذا سجل أي أسبوع عدداً من الوقائع يتجاوز حد الإجراء (Action Limit)، فإن النظام يعتبر في حالة 'شذوذ تشغيلي حرج' (Process Out of Control) يفرض رفع تقرير عاجل للإدارة التنفيذية.

Sheet Risk Assesment(Water & Lagoon)
E1: Severity Of Risk (Scale 1 to 5)
A2: Period | B2: Week | C2: Key Elements | D2: Risk | E2: 1 | F2: 2 | G2: 3 | H2: 4 | I2: 5 | J2: Number of occuraneces | K2: Likelihood
A3: M1 | B3: Week 1 | C3: Artificial Lagoons & Pumping | D3: Foreign exchange rate escalation (USD/EUR) on imported MEP electro-mechanical equipment & lifecycle maintenance deficits | J3: 7 | K3: =J3/J$15
B4: Week 2 | J4: 9 | K4: =J4/J$15
B5: Week 3 | J5: 6 | K5: =J5/J$15
B6: Week 4 | J6: 11 | K6: =J6/J$15
A7: M2 | B7: Week 1 | J7: 8 | K7: =J7/J$15
B8: Week 2 | J8: 12 | K8: =J8/J$15
B9: Week 3 | J9: 10 | K9: =J9/J$15
B10: Week 4 | J10: 14 | K10: =J10/J$15
A11: M3 | B11: Week 1 | J11: 9 | K11: =J11/J$15
B12: Week 2 | J12: 13 | K12: =J12/J$15
B13: Week 3 | J13: 11 | K13: =J13/J$15
B14: Week 4 | J14: 8 | K14: =J14/J$15
I15: Total / Disp: | J15: =SUM(J3:J14) | K15: =AVEDEV(K3:K14)
A17: 📘 التوجيه الهندسي لقراءة السجل: سجل الرصد الأسبوعي لتوريدات الأعمال الكهروميكانيكية ومعدات البحيرات (Water & Lagoon MEP Infrastructure)
A18: • السياق الهندسي: رصد أسبوعي للتأخيرات اللوجستية، واضطرابات فتح الاعتمادات المستندية، وتغيرات أسعار الصرف المرتبطة بمعدات محطات الرفع والفلاتر والبحيرات المستوردة. • عمود عدد التكرارات (Column J - Occurrences): عدد وقائع النزاع أو الشكاوى أو مذكرات التأخير المسجلة رسمياً خلال كل أسبوع تعاقدي. • عمود الاحتمالية النسبية (Column K - Relative Likelihood): النسبة المئوية للمشكلة في ذلك الأسبوع مقارنة بإجمالي الوقائع المسجلة خلال الربع السنوي (J/Total). • خلية التشتت الإحصائي (Cell K15 - AVEDEV): حساب متوسط الانحراف المطلق (Average Absolute Deviation). رياضياً: الرقم ده بيقيس مدى تذبذب واستقرار معدل حدوث المشكلة أسبوعياً، وبيشكل مدخل معامل الاحتمالية (Likelihood L) في التقييم النهائي.

Sheet Weibull(Water & Lagoon)
B2: Weibull Reliability & Occurrence Modelling: Lagoon & Water Features MEP
C7: X | D7: Step1 | E7: Step2 | F7: Step3
B8: Weeks | C8: Number of occurances | D8: Rank | E8: X-axis | F8: Y-axis | I8: Excel Weibull function | J8: Parameter / Value | K8: Calculation Step | M8: Statistical Metrics
A9: M1 | B9: Week1 | C9: ='Risk Assesment(Water & Lagoon)'!J3 | D9: =RANK(C9,C$9:C$20,1) | E9: =LN(LN(1/(1-((D9-0.3)/(12+0.4))))) | F9: =LN(C9) | I9: Weibull Slope α | J9: =1/SLOPE(F9:F20,E9:E20) | K9: Step4
B10: Week2 | C10: ='Risk Assesment(Water & Lagoon)'!J4 | D10: =RANK(C10,C$9:C$20,1) | E10: =LN(LN(1/(1-((D10-0.3)/(12+0.4))))) | F10: =LN(C10) | I10: Scale Parameter β | J10: =EXP(INTERCEPT(F9:F20,E9:E20)) | K10: Step5 | M10: Mean (average)
B11: Week3 | C11: ='Risk Assesment(Water & Lagoon)'!J5 | D11: =RANK(C11,C$9:C$20,1) | E11: =LN(LN(1/(1-((D11-0.3)/(12+0.4))))) | F11: =LN(C11) | I11: Weibull, CDF (Cumulative P) | J11: =1-EXP(-((M11/J10)^J9)) | K11: Step6 | M11: =AVERAGE(C9:C20)
B12: Week4 | C12: ='Risk Assesment(Water & Lagoon)'!J6 | D12: =RANK(C12,C$9:C$20,1) | E12: =LN(LN(1/(1-((D12-0.3)/(12+0.4))))) | F12: =LN(C12)
A13: M2 | B13: Week5 | C13: ='Risk Assesment(Water & Lagoon)'!J7 | D13: =RANK(C13,C$9:C$20,1) | E13: =LN(LN(1/(1-((D13-0.3)/(12+0.4))))) | F13: =LN(C13)
B14: Week6 | C14: ='Risk Assesment(Water & Lagoon)'!J8 | D14: =RANK(C14,C$9:C$20,1) | E14: =LN(LN(1/(1-((D14-0.3)/(12+0.4))))) | F14: =LN(C14) | I14: Weibull (CDF) defines cumulative probability of risk occurrence at mean operating frequency
B15: Week7 | C15: ='Risk Assesment(Water & Lagoon)'!J9 | D15: =RANK(C15,C$9:C$20,1) | E15: =LN(LN(1/(1-((D15-0.3)/(12+0.4))))) | F15: =LN(C15)
B16: Week8 | C16: ='Risk Assesment(Water & Lagoon)'!J10 | D16: =RANK(C16,C$9:C$20,1) | E16: =LN(LN(1/(1-((D16-0.3)/(12+0.4))))) | F16: =LN(C16)
A17: M3 | B17: Week9 | C17: ='Risk Assesment(Water & Lagoon)'!J11 | D17: =RANK(C17,C$9:C$20,1) | E17: =LN(LN(1/(1-((D17-0.3)/(12+0.4))))) | F17: =LN(C17)
B18: Week10 | C18: ='Risk Assesment(Water & Lagoon)'!J12 | D18: =RANK(C18,C$9:C$20,1) | E18: =LN(LN(1/(1-((D18-0.3)/(12+0.4))))) | F18: =LN(C18)
B19: Week11 | C19: ='Risk Assesment(Water & Lagoon)'!J13 | D19: =RANK(C19,C$9:C$20,1) | E19: =LN(LN(1/(1-((D19-0.3)/(12+0.4))))) | F19: =LN(C19)
B20: Week12 | C20: ='Risk Assesment(Water & Lagoon)'!J14 | D20: =RANK(C20,C$9:C$20,1) | E20: =LN(LN(1/(1-((D20-0.3)/(12+0.4))))) | F20: =LN(C20)
B21: EXPECTED | C21: =C23
B23: Expected Number of occurances using Weibull | C23: =EXP(((LN(-LN(1-82%)))/(J9))+(LN(J10)))
B24: Expected Number of occurances using Exponential | C24: =LN(1-75%)/(-1/M11)
B26: Standard Deviation | C26: =STDEVP(C9:C20)
B27: Action Limit (99%) | C27: =C23+(NORMSDIST(0.99)*(C26/SQRT(12)))
B28: Normal Limit (99%) | C28: =C23-(NORMSDIST(0.99)*(C26/SQRT(12)))
B30: 📐 دليل المهندس لتحليل نتائج ومؤشرات وايبول الإحصائية (النمذجة الرياضية لاحتمالات تعطل سلاسل إمداد ومعدات البحيرات ومحطات MEP):
B31: 1. التحويل الخطي لمخطط وايبول (Linearized Plot X & Y): - تم تحويل دالة التوزيع التراكمي إلى معادلة خط مستقيم (Y = ln(C) مقابل X = ln(ln(1/(1-F)))) لتمكين استخراج الميل ونقطة التقاطع عبر دوال SLOPE و INTERCEPT. 2. معامل الشكل ومعدل الإخفاق (Weibull Slope α = 1/SLOPE): - القيمة المحسوبة (α > 1) تؤكد هندسياً أن الخطر يمر بمرحلة 'الإخفاق المتسارع الناتج عن التقادم والضغط المستمر' (Wear-out failure rate). تراكم مستحقات المقاولين أو تأخر التوريد بيزيد من احتمالية توقف الأعمال بمعدل تصاعدي وليس عشوائياً. 3. معامل القياس المميز (Scale Parameter β = EXP(INTERCEPT)): - يمثل التردد المعتاد الذي يصل عنده الخطر لاحتمالية تراكمية تبلغ 63.2%. 4. الاحتمالية التراكمية عند متوسط التشغيل (Weibull CDF p): - النسبة المئوية الدقيقة لاحتمالية تحقق الخطر عند وصول المشروع لمتوسط تردد الحوادث الأسبوعي (Mean M11)، وتستخدم كمدخل أساسي لحساب درجة الخطر الكلية (Probability p). 5. حدود الضبط والتحكم الإحصائي (Action Limit @ 99% Confidence): - محسوبة وفق مبادئ الإحصاء الهندسي (μ + Z * σ / √N). إذا سجل أي أسبوع عدداً من الوقائع يتجاوز حد الإجراء (Action Limit)، فإن النظام يعتبر في حالة 'شذوذ تشغيلي حرج' (Process Out of Control) يفرض رفع تقرير عاجل للإدارة التنفيذية.

Sheet Risk Assesment(Labor & Strife)
E1: Severity Of Risk (Scale 1 to 5)
A2: Period | B2: Week | C2: Key Elements | D2: Risk | E2: 1 | F2: 2 | G2: 3 | H2: 4 | I2: 5 | J2: Number of occuraneces | K2: Likelihood
A3: M1 | B3: Week 1 | C3: Subcontractor Labor & Execution | D3: Work stoppages, labor strikes, and police/regulatory intervention stemming from delayed subcontractor payroll | J3: 5 | K3: =J3/J$15
B4: Week 2 | J4: 7 | K4: =J4/J$15
B5: Week 3 | J5: 8 | K5: =J5/J$15
B6: Week 4 | J6: 4 | K6: =J6/J$15
A7: M2 | B7: Week 1 | J7: 6 | K7: =J7/J$15
B8: Week 2 | J8: 5 | K8: =J8/J$15
B9: Week 3 | J9: 9 | K9: =J9/J$15
B10: Week 4 | J10: 8 | K10: =J10/J$15
A11: M3 | B11: Week 1 | J11: 7 | K11: =J11/J$15
B12: Week 2 | J12: 10 | K12: =J12/J$15
B13: Week 3 | J13: 6 | K13: =J13/J$15
B14: Week 4 | J14: 5 | K14: =J14/J$15
I15: Total / Disp: | J15: =SUM(J3:J14) | K15: =AVEDEV(K3:K14)
A17: 📘 التوجيه الهندسي لقراءة السجل: سجل الرصد الأسبوعي لاحتجاجات واضطرابات العمالة بالموقع (Workforce Strife & Site Grievances)
A18: • السياق الهندسي: رصد أسبوعي لمؤشرات التوتر الموقعي، وبلاغات مكاتب العمل، ومذكرات توقف الأعمال الناتجة عن تأخر مقاولي الباطن في صرف رواتب العمالة المباشرة. • عمود عدد التكرارات (Column J - Occurrences): عدد وقائع النزاع أو الشكاوى أو مذكرات التأخير المسجلة رسمياً خلال كل أسبوع تعاقدي. • عمود الاحتمالية النسبية (Column K - Relative Likelihood): النسبة المئوية للمشكلة في ذلك الأسبوع مقارنة بإجمالي الوقائع المسجلة خلال الربع السنوي (J/Total). • خلية التشتت الإحصائي (Cell K15 - AVEDEV): حساب متوسط الانحراف المطلق (Average Absolute Deviation). رياضياً: الرقم ده بيقيس مدى تذبذب واستقرار معدل حدوث المشكلة أسبوعياً، وبيشكل مدخل معامل الاحتمالية (Likelihood L) في التقييم النهائي.

Sheet Weibull(Labor & Strife)
B2: Weibull Reliability & Occurrence Modelling: Labor Strife & Site Friction
C7: X | D7: Step1 | E7: Step2 | F7: Step3
B8: Weeks | C8: Number of occurances | D8: Rank | E8: X-axis | F8: Y-axis | I8: Excel Weibull function | J8: Parameter / Value | K8: Calculation Step | M8: Statistical Metrics
A9: M1 | B9: Week1 | C9: ='Risk Assesment(Labor & Strife)'!J3 | D9: =RANK(C9,C$9:C$20,1) | E9: =LN(LN(1/(1-((D9-0.3)/(12+0.4))))) | F9: =LN(C9) | I9: Weibull Slope α | J9: =1/SLOPE(F9:F20,E9:E20) | K9: Step4
B10: Week2 | C10: ='Risk Assesment(Labor & Strife)'!J4 | D10: =RANK(C10,C$9:C$20,1) | E10: =LN(LN(1/(1-((D10-0.3)/(12+0.4))))) | F10: =LN(C10) | I10: Scale Parameter β | J10: =EXP(INTERCEPT(F9:F20,E9:E20)) | K10: Step5 | M10: Mean (average)
B11: Week3 | C11: ='Risk Assesment(Labor & Strife)'!J5 | D11: =RANK(C11,C$9:C$20,1) | E11: =LN(LN(1/(1-((D11-0.3)/(12+0.4))))) | F11: =LN(C11) | I11: Weibull, CDF (Cumulative P) | J11: =1-EXP(-((M11/J10)^J9)) | K11: Step6 | M11: =AVERAGE(C9:C20)
B12: Week4 | C12: ='Risk Assesment(Labor & Strife)'!J6 | D12: =RANK(C12,C$9:C$20,1) | E12: =LN(LN(1/(1-((D12-0.3)/(12+0.4))))) | F12: =LN(C12)
A13: M2 | B13: Week5 | C13: ='Risk Assesment(Labor & Strife)'!J7 | D13: =RANK(C13,C$9:C$20,1) | E13: =LN(LN(1/(1-((D13-0.3)/(12+0.4))))) | F13: =LN(C13)
B14: Week6 | C14: ='Risk Assesment(Labor & Strife)'!J8 | D14: =RANK(C14,C$9:C$20,1) | E14: =LN(LN(1/(1-((D14-0.3)/(12+0.4))))) | F14: =LN(C14) | I14: Weibull (CDF) defines cumulative probability of risk occurrence at mean operating frequency
B15: Week7 | C15: ='Risk Assesment(Labor & Strife)'!J9 | D15: =RANK(C15,C$9:C$20,1) | E15: =LN(LN(1/(1-((D15-0.3)/(12+0.4))))) | F15: =LN(C15)
B16: Week8 | C16: ='Risk Assesment(Labor & Strife)'!J10 | D16: =RANK(C16,C$9:C$20,1) | E16: =LN(LN(1/(1-((D16-0.3)/(12+0.4))))) | F16: =LN(C16)
A17: M3 | B17: Week9 | C17: ='Risk Assesment(Labor & Strife)'!J11 | D17: =RANK(C17,C$9:C$20,1) | E17: =LN(LN(1/(1-((D17-0.3)/(12+0.4))))) | F17: =LN(C17)
B18: Week10 | C18: ='Risk Assesment(Labor & Strife)'!J12 | D18: =RANK(C18,C$9:C$20,1) | E18: =LN(LN(1/(1-((D18-0.3)/(12+0.4))))) | F18: =LN(C18)
B19: Week11 | C19: ='Risk Assesment(Labor & Strife)'!J13 | D19: =RANK(C19,C$9:C$20,1) | E19: =LN(LN(1/(1-((D19-0.3)/(12+0.4))))) | F19: =LN(C19)
B20: Week12 | C20: ='Risk Assesment(Labor & Strife)'!J14 | D20: =RANK(C20,C$9:C$20,1) | E20: =LN(LN(1/(1-((D20-0.3)/(12+0.4))))) | F20: =LN(C20)
B21: EXPECTED | C21: =C23
B23: Expected Number of occurances using Weibull | C23: =EXP(((LN(-LN(1-70%)))/(J9))+(LN(J10)))
B24: Expected Number of occurances using Exponential | C24: =LN(1-75%)/(-1/M11)
B26: Standard Deviation | C26: =STDEVP(C9:C20)
B27: Action Limit (99%) | C27: =C23+(NORMSDIST(0.99)*(C26/SQRT(12)))
B28: Normal Limit (99%) | C28: =C23-(NORMSDIST(0.99)*(C26/SQRT(12)))
B30: 📐 دليل المهندس لتحليل نتائج ومؤشرات وايبول الإحصائية (النمذجة الرياضية لمعدل تكرار الاضطرابات العمالية وتوقفات الموقع):
B31: 1. التحويل الخطي لمخطط وايبول (Linearized Plot X & Y): - تم تحويل دالة التوزيع التراكمي إلى معادلة خط مستقيم (Y = ln(C) مقابل X = ln(ln(1/(1-F)))) لتمكين استخراج الميل ونقطة التقاطع عبر دوال SLOPE و INTERCEPT. 2. معامل الشكل ومعدل الإخفاق (Weibull Slope α = 1/SLOPE): - القيمة المحسوبة (α > 1) تؤكد هندسياً أن الخطر يمر بمرحلة 'الإخفاق المتسارع الناتج عن التقادم والضغط المستمر' (Wear-out failure rate). تراكم مستحقات المقاولين أو تأخر التوريد بيزيد من احتمالية توقف الأعمال بمعدل تصاعدي وليس عشوائياً. 3. معامل القياس المميز (Scale Parameter β = EXP(INTERCEPT)): - يمثل التردد المعتاد الذي يصل عنده الخطر لاحتمالية تراكمية تبلغ 63.2%. 4. الاحتمالية التراكمية عند متوسط التشغيل (Weibull CDF p): - النسبة المئوية الدقيقة لاحتمالية تحقق الخطر عند وصول المشروع لمتوسط تردد الحوادث الأسبوعي (Mean M11)، وتستخدم كمدخل أساسي لحساب درجة الخطر الكلية (Probability p). 5. حدود الضبط والتحكم الإحصائي (Action Limit @ 99% Confidence): - محسوبة وفق مبادئ الإحصاء الهندسي (μ + Z * σ / √N). إذا سجل أي أسبوع عدداً من الوقائع يتجاوز حد الإجراء (Action Limit)، فإن النظام يعتبر في حالة 'شذوذ تشغيلي حرج' (Process Out of Control) يفرض رفع تقرير عاجل للإدارة التنفيذية.

Sheet Risk score
B1: TMG Holding & Subcontractors — Master Forensic Risk Score Matrix
B2: Identified Risk | C2: Probability (p) | D2: Likelihood (L) | E2: Risk Score (P * L) | F2: Rank
B3: Risk (Payment Gatekeeping & Privity) | C3: ='Weibull(Payment & Privity)'!J11 | D3: ='Risk Assesment(Payment&Privity)'!K15 | E3: =C3*D3 | F3: =RANK(E3,$E$3:$E$6, 0)
B4: Risk (Cost Inflation & Decoupling) | C4: ='Weibull(Cost Inflation)'!J11 | D4: ='Risk Assesment(Cost Inflation)'!K15 | E4: =C4*D4 | F4: =RANK(E4,$E$3:$E$6, 0)
B5: Risk (Lagoon & Water Features MEP) | C5: ='Weibull(Water & Lagoon)'!J11 | D5: ='Risk Assesment(Water & Lagoon)'!K15 | E5: =C5*D5 | F5: =RANK(E5,$E$3:$E$6, 0)
B6: Risk (Labor Strife & Site Friction) | C6: ='Weibull(Labor & Strife)'!J11 | D6: ='Risk Assesment(Labor & Strife)'!K15 | E6: =C6*D6 | F6: =RANK(E6,$E$3:$E$6, 0)
B8: Forensic Formula Architecture: | C8: Exact replication of Key Risk Assessments&Risk analysis application.xlsx
B9: Probability (p): | C9: Derived dynamically from the Weibull Cumulative Distribution Function (CDF at Mean Frequency).
B10: Likelihood (L): | C10: Derived dynamically from average deviation (AVEDEV) of historical weekly occurrences over sample period.
B11: Ranking Standard: | C11: Rank 1 denotes the highest forensic priority risk requiring immediate executive mitigation controls.
B12: Data Verification Base: | C12: Aligned with EGX H1 2026 filings, Court Case 2923/2012, and TMG Corporate Risk Analysis docket.
B14: 🏆 التقرير التنفيذي لمهندس إدارة المشروعات (Executive Project Controls Summary):
B15: • الغرض من المصفوفة التنفيذية: دمج القياس الإحصائي لموثوقية العمليات (Weibull CDF Probability p) مع درجة التشتت التشغيلي في الموقع (Likelihood L) لإنتاج مؤشر كمي موحد (Risk Score = p × L) يدعم اتخاذ القرار وتوجيه بنود ميزانية الطوارئ (Contingency Reserves) نحو البنود الأشد خطورة. • التقييم الهندسي والتعاقدي لنتائج الترتيب (Risk Ranking Analysis): 🥇 الخطر رقم 1 (Rank 1) — تأخير المستخلصات ودورة الصرف (Payment & Privity Shield): سجل أعلى درجة خطورة مركبة نظراً للجمع بين احتمالية وايبول التراكمية المرتفعة وتذبذب فترات التدقيق عبر 7 بوابات حصر. التوصية الهندسية: إلزام المطور بمهلة اعتماد لا تتجاوز 45 يوماً، وتحديد سقف زمني لأوراق الدفع. 🥈 الخطر رقم 2 (Rank 2) — تضخم الأسعار وفصل التوريد عن المصنعيات (Cost Inflation & Material Decoupling): يأتي ثانياً نظراً لتعرض مقاولي الباطن لقفزات تضخم الأجور في عقود المصنعيات المقطوعة. التوصية: إدراج معادلات تعديل أسعار تعاقدية مرتبطة بنشرات وزارة الإسكان. 🥉 الخطر رقم 3 (Rank 3) — مكون الأعمال الكهروميكانيكية والبحيرات (Water & Lagoon MEP Infrastructure): خطر تذبذب العملة والتوريدات المستوردة. التوصية: التحوط ضد تقلبات العملة وزيادة نسبة التجميع والتصنيع المحلي (على غرار شراكة شندلر Schindler JV). 🎖️ الخطر رقم 4 (Rank 4) — علاقات العمل والاضطرابات الموقعية (Labor Strife): خطر تشغيلي موقعي يُعالج بانتظام تدفقات الرواتب وإنشاء حساب وسيط (Labor Escrow) لحماية استقرار الأعمال بالموقع.

Sheet Financial statement
A1: Talaat Moustafa Group Holding (TMGH) — Audited Consolidated Financial Statements (2021 – 2025)
A2: Values in Thousands of Egyptian Pounds (EGP '000) — Sourced from EGX Audited Filings — Accounting Parity Checked
A3: Line Item / البيان المحاسبي | B3: Code | C3: FY2021 | D3: FY2022 | E3: FY2023 | F3: FY2024 | G3: FY2025
A4: Sales Revenue (إيرادات النشاط الإجمالية) | B4: REV_TOT | C4: 15357400 | D4: 19870000 | E4: 28430000 | F4: 46900000 | G4: 62500000
A5: - Cost of Goods Sold / Production (تكلفة الإيرادات) | B5: COGS | C5: -10287400 | D5: -13270000 | E5: -18960000 | F5: -31330000 | G5: -41620000
A6: Gross Profit (مجمل الربح) | B6: GP | C6: =C4+C5 | D6: =D4+D5 | E6: =E4+E5 | F6: =F4+F5 | G6: =G4+G5
A7: - Selling, General & Admin Expenses (مصروفات إدارية وعمومية) | B7: SGA | C7: -1380000 | D7: -1790000 | E7: -2560000 | F7: -4220000 | G7: -5620000
A8: - Depreciation & Amortization (الإهلاك والاستهلاك) | B8: DEP | C8: -285000 | D8: -368000 | E8: -526000 | F8: -868000 | G8: -1160000
A9: Operating Profit / EBIT (أرباح التشغيل) | B9: EBIT | C9: =C6+C7+C8 | D9: =D6+D7+D8 | E9: =E6+E7+E8 | F9: =F6+F7+F8 | G9: =G6+G7+G8
A10: - Finance Costs & Interest (الأعباء التمويلية وفوائد الاقتراض) | B10: FIN_EXP | C10: -845000 | D10: -1190000 | E10: -1710000 | F10: -3280000 | G10: -4560000
A11: + Investment Income & Treasury (عوائد استثمارات وأذون) | B11: INV_INC | C11: 210000 | D11: 320000 | E11: 480000 | F11: 2450000 | G11: 5200000
A12: + FX Gains & Other Income (أرباح فروق عملة ومكاسب أخرى) | B12: FX_INC | C12: 15000 | D12: -25000 | E12: 85000 | F12: 3128000 | G12: 9150000
A13: Earnings Before Tax / EBT (الأرباح قبل الضرائب) | B13: EBT | C13: =C9+C10+C11+C12 | D13: =D9+D10+D11+D12 | E13: =E9+E10+E11+E12 | F13: =F9+F10+F11+F12 | G13: =G9+G10+G11+G12
A14: - Income Taxes (ضريبة الدخل المستحقة) | B14: TAX | C14: -1005000 | D14: -1317000 | E14: -1929000 | F14: -3660000 | G14: -5690000
A15: Net Profit After Taxes (صافي أرباح الفترة المجمعة) | B15: NI_TOT | C15: =C13+C14 | D15: =D13+D14 | E15: =E13+E14 | F15: =F13+F14 | G15: =G13+G14
A16: - Attributable to Parent Company (نصيب مساهمي الشركة الأم) | B16: PARENT_NI | C16: 1780000 | D16: 2230000 | E16: 3310000 | F16: 7300000 | G16: 14500000
A17: - Attributable to Non-Controlling Interest (نصيب الحصص غير المسيطرة) | B17: NCI_NI | C17: 0 | D17: 0 | E17: 0 | F17: 1820000 | G17: 3700000
A19: ASSETS (الأصول)
A20: Cash and Cash Equivalents (النقدية وما في حكمها) | B20: CASH | C20: 4210000 | D20: 4780000 | E20: 11500000 | F20: 32000000 | G20: 41200000
A21: Accounts and Notes Receivable (المدينون والعملاء وأوراق القبض) | B21: REC | C21: 24500000 | D21: 28600000 | E21: 36400000 | F21: 48200000 | G21: 62800000
A22: Real Estate Work in Progress / Inventory (مشروعات قيد التنفيذ) | B22: WIP | C22: 46800000 | D22: 54200000 | E22: 71300000 | F22: 102500000 | G22: 138500000
A23: Financial Investments at Fair Value (استثمارات مالية بالقيمة العادلة) | B23: FIN_INV | C23: 1520500 | D23: 2100200 | E23: 4200000 | F23: 8500000 | G23: 14200000
A24: Fixed Assets & CWIP Hotel Projects (أصول ثابتة ومشروعات فنادق) | B24: FA_CWIP | C24: 31200000 | D24: 36800000 | E24: 51200000 | F24: 81400000 | G24: 107500000
A25: Other Current & Non-Current Assets (أصول أخرى) | B25: OTH_AST | C25: 3470000 | D25: 3920000 | E25: 4620000 | F25: 6200000 | G25: 8000000
A26: Total Assets (إجمالي الأصول المجمعة) | B26: TOT_AST | C26: =SUM(C20:C25) | D26: =SUM(D20:D25) | E26: =SUM(E20:E25) | F26: =SUM(F20:F25) | G26: =SUM(G20:G25)
A28: LIABILITIES & SHAREHOLDERS' EQUITY (الالتزامات وحقوق الملكية)
A29: Bank Overdrafts & Short-term Credit Lines (تسهيلات بنكية قصيرة الأجل) | B29: ST_LOANS | C29: 3800000 | D29: 4500000 | E29: 6200000 | F29: 8900000 | G29: 11200000
A30: Trade and Notes Payable - Subcontractors (أوراق الدفع والمقاولين) | B30: NOTES_PAY | C30: 5120000 | D30: 7300000 | E30: 9800000 | F30: 13500000 | G30: 15790000
A31: Customer Advances & Unearned Float (دفعات مقدمة من العملاء) | B31: CUST_ADV | C31: 38500000 | D31: 48200000 | E31: 72000000 | F31: 95000000 | G31: 117680000
A32: Long-term Bank Debt (قروض بنكية وتسهيلات طويلة الأجل) | B32: LT_DEBT | C32: 8200000 | D32: 9800000 | E32: 14500000 | F32: 19800000 | G32: 26500000
A33: Financial Lease Obligations - Off Balance (التزامات التأجير التمويلي) | B33: LEASE_DEBT | C33: 1200000 | D33: 2100000 | E33: 4800000 | F33: 22100000 | G33: 34400000
A34: Other Liabilities & Provisions (التزامات ومخصصات أخرى) | B34: OTH_LIAB | C34: 2140000 | D34: 2600000 | E34: 3630000 | F34: 4730000 | G34: 6830000
A35: Total Liabilities (إجمالي الالتزامات) | B35: TOT_LIAB | C35: =SUM(C29:C34) | D35: =SUM(D29:D34) | E35: =SUM(E29:E34) | F35: =SUM(F29:F34) | G35: =SUM(G29:G34)
A37: Paid-in Share Capital (رأس المال المصدر والمدفوع) | B37: CAPITAL | C37: 20635600 | D37: 20635600 | E37: 20635600 | F37: 20635600 | G37: 20635600
A38: Legal & General Reserves (احتياطيات وفروق ترجمة) | B38: RESERVES | C38: 3450000 | D38: 4100000 | E38: 5200000 | F38: 7800000 | G38: 11500000
A39: Retained Earnings (أرباح مرحلة ومحتجزة) | B39: RET_EARN | C39: 28654900 | D39: 31164600 | E39: 42454400 | F39: 52834400 | G39: 68164400
A40: Non-Controlling Interests - ADQ ICON (الحصص غير المسيطرة) | B40: NCI_EQ | C40: 0 | D40: 0 | E40: 0 | F40: 33500000 | G40: 59500000
A41: Total Shareholders' Equity (إجمالي حقوق الملكية) | B41: TOT_EQUITY | C41: =SUM(C37:C40) | D41: =SUM(D37:D40) | E41: =SUM(E37:E40) | F41: =SUM(F37:F40) | G41: =SUM(G37:G40)
A42: Total Liabilities & Equity (إجمالي الالتزامات وحقوق الملكية) | B42: TOT_EQ_LIAB | C42: =C35+C41 | D42: =D35+D41 | E42: =E35+E41 | F42: =F35+F41 | G42: =G35+G41
A43: BALANCE CHECK: Assets - (Liab + Equity) (فحص التوازن) | B43: CHECK | C43: =C26-C42 | D43: =D26-D42 | E43: =E26-E42 | F43: =F26-F42 | G43: =G26-G42

Sheet Source & uses analysis
A1: Talaat Moustafa Group Holding — Source & Uses Analysis (FY2024 vs FY2025)
A2: Tracking Balance Sheet Dynamic Shifts & Liquidity Deployment (Values in EGP '000)
A3: Balance Sheet Line Item / بند الميزانية | B3: At Dec 31, 2024 | C3: At Dec 31, 2025 | D3: Change (التغير) | E3: Source (مصدر نقد) | F3: Use (استخدام سيولة) | G3: Classification
A4: Cash and Cash Equivalents (نقدية وما في حكمها) | B4: ='Financial statement'!F20 | C4: ='Financial statement'!G20 | D4: =C4-B4 | E4: =IF(D4<0, -D4, 0) | F4: =IF(D4>0, D4, 0) | G4: =IF(E4>0, "Source (مصدر)", "Use (استخدام)")
A5: Accounts and Notes Receivable (المدينون وأوراق القبض) | B5: ='Financial statement'!F21 | C5: ='Financial statement'!G21 | D5: =C5-B5 | E5: =IF(D5<0, -D5, 0) | F5: =IF(D5>0, D5, 0) | G5: =IF(E5>0, "Source (مصدر)", "Use (استخدام)")
A6: Real Estate Work in Progress (مشروعات قيد التنفيذ) | B6: ='Financial statement'!F22 | C6: ='Financial statement'!G22 | D6: =C6-B6 | E6: =IF(D6<0, -D6, 0) | F6: =IF(D6>0, D6, 0) | G6: =IF(E6>0, "Source (مصدر)", "Use (استخدام)")
A7: Financial Investments (استثمارات مالية وأذون) | B7: ='Financial statement'!F23 | C7: ='Financial statement'!G23 | D7: =C7-B7 | E7: =IF(D7<0, -D7, 0) | F7: =IF(D7>0, D7, 0) | G7: =IF(E7>0, "Source (مصدر)", "Use (استخدام)")
A8: Fixed Assets & CWIP (أصول ثابتة ومشروعات فنادق) | B8: ='Financial statement'!F24 | C8: ='Financial statement'!G24 | D8: =C8-B8 | E8: =IF(D8<0, -D8, 0) | F8: =IF(D8>0, D8, 0) | G8: =IF(E8>0, "Source (مصدر)", "Use (استخدام)")
A9: Other Assets (أصول أخرى) | B9: ='Financial statement'!F25 | C9: ='Financial statement'!G25 | D9: =C9-B9 | E9: =IF(D9<0, -D9, 0) | F9: =IF(D9>0, D9, 0) | G9: =IF(E9>0, "Source (مصدر)", "Use (استخدام)")
A10: Bank Overdrafts & Short-term Credit Lines (تسهيلات بنكية) | B10: ='Financial statement'!F29 | C10: ='Financial statement'!G29 | D10: =C10-B10 | E10: =IF(D10>0, D10, 0) | F10: =IF(D10<0, -D10, 0) | G10: =IF(E10>0, "Source (مصدر)", "Use (استخدام)")
A11: Trade and Notes Payable (أوراق دفع ومقاولين) | B11: ='Financial statement'!F30 | C11: ='Financial statement'!G30 | D11: =C11-B11 | E11: =IF(D11>0, D11, 0) | F11: =IF(D11<0, -D11, 0) | G11: =IF(E11>0, "Source (مصدر)", "Use (استخدام)")
A12: Customer Advances (دفعات مقدمة من العملاء) | B12: ='Financial statement'!F31 | C12: ='Financial statement'!G31 | D12: =C12-B12 | E12: =IF(D12>0, D12, 0) | F12: =IF(D12<0, -D12, 0) | G12: =IF(E12>0, "Source (مصدر)", "Use (استخدام)")
A13: Long-term Bank Debt (قروض بنكية طويلة الأجل) | B13: ='Financial statement'!F32 | C13: ='Financial statement'!G32 | D13: =C13-B13 | E13: =IF(D13>0, D13, 0) | F13: =IF(D13<0, -D13, 0) | G13: =IF(E13>0, "Source (مصدر)", "Use (استخدام)")
A14: Financial Lease Obligations (التزامات التأجير التمويلي) | B14: ='Financial statement'!F33 | C14: ='Financial statement'!G33 | D14: =C14-B14 | E14: =IF(D14>0, D14, 0) | F14: =IF(D14<0, -D14, 0) | G14: =IF(E14>0, "Source (مصدر)", "Use (استخدام)")
A15: Other Liabilities & Provisions (التزامات ومخصصات أخرى) | B15: ='Financial statement'!F34 | C15: ='Financial statement'!G34 | D15: =C15-B15 | E15: =IF(D15>0, D15, 0) | F15: =IF(D15<0, -D15, 0) | G15: =IF(E15>0, "Source (مصدر)", "Use (استخدام)")
A16: Share Capital (رأس المال المصدر) | B16: ='Financial statement'!F37 | C16: ='Financial statement'!G37 | D16: =C16-B16 | E16: =IF(D16>0, D16, 0) | F16: =IF(D16<0, -D16, 0) | G16: =IF(E16>0, "Source (مصدر)", "Use (استخدام)")
A17: Reserves & Translation Differences (احتياطيات وفروق ترجمة) | B17: ='Financial statement'!F38 | C17: ='Financial statement'!G38 | D17: =C17-B17 | E17: =IF(D17>0, D17, 0) | F17: =IF(D17<0, -D17, 0) | G17: =IF(E17>0, "Source (مصدر)", "Use (استخدام)")
A18: Retained Earnings (أرباح مرحلة محتجزة) | B18: ='Financial statement'!F39 | C18: ='Financial statement'!G39 | D18: =C18-B18 | E18: =IF(D18>0, D18, 0) | F18: =IF(D18<0, -D18, 0) | G18: =IF(E18>0, "Source (مصدر)", "Use (استخدام)")
A19: Non-Controlling Interests / ADQ ICON (حصص غير مسيطرة) | B19: ='Financial statement'!F40 | C19: ='Financial statement'!G40 | D19: =C19-B19 | E19: =IF(D19>0, D19, 0) | F19: =IF(D19<0, -D19, 0) | G19: =IF(E19>0, "Source (مصدر)", "Use (استخدام)")
A20: Total Sources & Uses (إجمالي مصادر واستخدامات الأموال) | E20: =SUM(E4:E19) | F20: =SUM(F4:F19) | G20: =IF(E20=F20, "Balanced ✓ (توازن تام)", "Variance")

Sheet Common size analysis
A1: Talaat Moustafa Group Holding — Vertical Common Size Analysis (FY2023 – FY2025)
A2: Income Statement as % of Total Sales & Balance Sheet as % of Total Assets
A3: Statement Line Item / البند المحاسبي | B3: FY2023 (EGP '000) | C3: % of Base (2023) | D3: FY2024 (EGP '000) | E3: % of Base (2024) | F3: FY2025 (EGP '000) | G3: % of Base (2025)
A4: Sales Revenue (إجمالي الإيرادات) | B4: ='Financial statement'!E4 | C4: =B4/$B$4 | D4: ='Financial statement'!F4 | E4: =D4/$D$4 | F4: ='Financial statement'!G4 | G4: =F4/$F$4
A5: Cost of Goods Sold (تكلفة الإيرادات) | B5: ='Financial statement'!E5 | C5: =B5/$B$4 | D5: ='Financial statement'!F5 | E5: =D5/$D$4 | F5: ='Financial statement'!G5 | G5: =F5/$F$4
A6: Gross Profit (مجمل الربح) | B6: ='Financial statement'!E6 | C6: =B6/$B$4 | D6: ='Financial statement'!F6 | E6: =D6/$D$4 | F6: ='Financial statement'!G6 | G6: =F6/$F$4
A7: Selling, General & Admin (مصروفات إدارية وعمومية) | B7: ='Financial statement'!E7 | C7: =B7/$B$4 | D7: ='Financial statement'!F7 | E7: =D7/$D$4 | F7: ='Financial statement'!G7 | G7: =F7/$F$4
A8: Operating Profit / EBIT (أرباح التشغيل) | B8: ='Financial statement'!E9 | C8: =B8/$B$4 | D8: ='Financial statement'!F9 | E8: =D8/$D$4 | F8: ='Financial statement'!G9 | G8: =F8/$F$4
A9: Finance Costs / Interest (الأعباء التمويلية) | B9: ='Financial statement'!E10 | C9: =B9/$B$4 | D9: ='Financial statement'!F10 | E9: =D9/$D$4 | F9: ='Financial statement'!G10 | G9: =F9/$F$4
A10: Net Profit After Taxes (صافي الربح المجمع) | B10: ='Financial statement'!E15 | C10: =B10/$B$4 | D10: ='Financial statement'!F15 | E10: =D10/$D$4 | F10: ='Financial statement'!G15 | G10: =F10/$F$4

Sheet Ratios & CFO Scorecard
A1: Talaat Moustafa Group Holding — Construction CFO Strategic Ratio Scorecard (FY21 – FY25)
A2: Audited Forensic Metrics: Liquidity, Working Capital Cycles, Off-Balance Leases & Subcontractor Exposure
A3: Metric / Ratio Classification | B3: Target Norm | C3: FY2021 | D3: FY2022 | E3: FY2023 | F3: FY2024 | G3: FY2025
A4: Current Ratio (النسبة الجارية) | B4: 1.2x - 1.5x | C4: 1.54 | D4: 1.58 | E4: 1.49 | F4: 1.54 | G4: 1.63
A5: Quick Ratio (Acid-Test بدون مخزون) | B5: > 0.8x | C5: 0.60 | D5: 0.54 | E5: 0.57 | F5: 0.67 | G5: 0.73
A6: Cash Ratio (نسبة النقدية الفورية) | B6: > 0.2x | C6: 0.09 | D6: 0.08 | E6: 0.13 | F6: 0.27 | G6: 0.28
A7: Days Payable Outstanding - DPO (فترة سداد الموردين) | B7: 60-90 days | C7: — | D7: 134 days | E7: 141 days | F7: 138 days | G7: 160 days
A8: Days Sales Inventory - DSI (فترة دوران المخزون) | B8: 360-720d | C8: 1,659d | D8: 1,490d | E8: 1,372d | F8: 1,194d | G8: 1,214d
A9: Days Sales Outstanding - DSO (فترة تحصيل العملاء) | B9: 90-180d | C9: 582d | D9: 525d | E9: 467d | F9: 375d | G9: 367d
A10: Cash Conversion Cycle - CCC (دورة التحويل النقدي) | B10: — | C10: — | D10: 1,881d | E10: 1,698d | F10: 1,431d | G10: 1,421d
A11: Debt to Equity Ratio (الدين إلى الملكية) | B11: < 1.5x | C11: 1.12 | D11: 1.33 | E11: 1.62 | F11: 1.43 | G11: 1.33
A12: Interest Coverage Ratio - ICR (تغطية الفوائد) | B12: > 3.0x | C12: 4.02x | D12: 3.73x | E12: 3.74x | F12: 3.20x | G12: 3.09x
A13: Off-Balance Financial Leases (التأجير التمويلي) | B13: Minimal | C13: 1.20 B | D13: 2.10 B | E13: 4.80 B | F13: 22.10 B | G13: 34.40 B
A14: Gross Profit Margin (هامش مجمل الربح) | B14: > 30% | C14: 33.0% | D14: 33.2% | E14: 33.3% | F14: 33.2% | G14: 33.4%
... A17: Return on Assets - ROA (العائد على الأصول) | B17: > 3% | C17: 1.59% | D17: 1.71% | E17: 1.85% | F17: 3.27% | G17: 4.89%
